pyossia-1.0.0b9.data/purelib/pyossia/__init__.py
pyossia-1.0.0b9.data/purelib/pyossia/_version.py
pyossia-1.0.0b9.data/purelib/pyossia/ossia_python.cpython-36m-darwin.so
pyossia-1.0.0b9.data/purelib/pyossia/ossia_python.py
pyossia-1.0.0b9.dist-info/DESCRIPTION.rst
pyossia-1.0.0b9.dist-info/METADATA
pyossia-1.0.0b9.dist-info/RECORD
pyossia-1.0.0b9.dist-info/WHEEL
pyossia-1.0.0b9.dist-info/metadata.json
pyossia-1.0.0b9.dist-info/top_level.txt
